orm/__init__.py
orm/abc.py
orm/exceptions.py
orm/join.py
orm/table.py
py_tiny_orm-0.0.6.dist-info/LICENSE
py_tiny_orm-0.0.6.dist-info/METADATA
py_tiny_orm-0.0.6.dist-info/WHEEL
py_tiny_orm-0.0.6.dist-info/top_level.txt
py_tiny_orm-0.0.6.dist-info/RECORD
